migverify/__init__.py
migverify/migverify.py
migverify/run_migverify.py
migverify-0.1.dist-info/entry_points.txt
migverify-0.1.dist-info/LICENSE
migverify-0.1.dist-info/WHEEL
migverify-0.1.dist-info/METADATA
migverify-0.1.dist-info/RECORD
