Metadata-Version: 1.2
Name: migverify
Version: 0.1
Summary: A script to parse and verify migrate-n infiles with loads
Home-page: https://github.com/andersgs/migverify
License: UNKNOWN
Keywords: migrate-n
Author: Anders Goncalves da Silva
Author-email: andersgs@gmail.com
Requires-Python: >=3.6
Classifier: License :: OSI Approved :: GNU General Public License v3 or later (GPLv3+)
Classifier: Development Status :: 4 - Beta
Classifier: Topic :: Scientific/Engineering :: Bio-Informatics
Classifier: Intended Audience :: Science/Research
Requires-Dist: click (>=6.6)
